main.py
botnik_generator-1.0.0.dist-info/LICENSE
botnik_generator-1.0.0.dist-info/METADATA
botnik_generator-1.0.0.dist-info/WHEEL
botnik_generator-1.0.0.dist-info/entry_points.txt
botnik_generator-1.0.0.dist-info/top_level.txt
botnik_generator-1.0.0.dist-info/RECORD
