Metadata-Version: 2.1
Name: botnik-generator
Version: 1.0.0
Summary: Create a new Botnik AI predictive keyboard from a youtube playlist by downloading its subtitles.
Home-page: https://github.com/JMcB17/botnik-generator
Author: JMcB
Author-email: joel.mcbride1@live.com
License: GPLv3
Platform: UNKNOWN
Classifier: Programming Language :: Python :: 3
Classifier: License :: OSI Approved :: GNU General Public License v3 (GPLv3)
Classifier: Development Status :: 4 - Beta
Classifier: Environment :: Console
Requires-Python: >=3
Requires-Dist: youtube-dl
Requires-Dist: beautifulsoup4
